zarrita/__init__.py
zarrita/array.py
zarrita/array_v2.py
zarrita/codecs.py
zarrita/common.py
zarrita/group.py
zarrita/group_v2.py
zarrita/indexing.py
zarrita/metadata.py
zarrita/sharding.py
zarrita/store.py
zarrita/sync.py
zarrita-0.2.7.dist-info/LICENSE
zarrita-0.2.7.dist-info/METADATA
zarrita-0.2.7.dist-info/WHEEL
zarrita-0.2.7.dist-info/RECORD
