Metadata-Version: 2.1
Name: zarrita
Version: 0.2.7
Summary: 
License: MIT
Author: Norman Rzepka
Author-email: code@normanrz.com
Requires-Python: >=3.8,<4.0
Classifier: License :: OSI Approved :: MIT License
Classifier: Programming Language :: Python :: 3
Classifier: Programming Language :: Python :: 3.8
Classifier: Programming Language :: Python :: 3.9
Classifier: Programming Language :: Python :: 3.10
Classifier: Programming Language :: Python :: 3.11
Classifier: Programming Language :: Python :: 3.12
Requires-Dist: attrs (>=22.2.0)
Requires-Dist: cattrs (>=22.2.0)
Requires-Dist: crc32c (>=2.3)
Requires-Dist: fsspec (>=2022.0.0)
Requires-Dist: numcodecs (>=0.11,<1.0)
Requires-Dist: numpy (>=1.22,<3.0)
Requires-Dist: zstandard (>=0.21.0,<0.22.0)
